
{
  "1": "Righteous Fury",
  "2": "Blessing of Might",
  "3": "Repentance",
  "4": "Retribution Aura",
  "5": "Hand of Freedom",
  "6": "Consecration",
  "7": "Devotion Aura",
  "8": "Hand of Protection",
  "9": "Hand of Salvation",
  "10": "Seal of Justice (Stun)",
  "11": "Judgement of Righteousness",
  "12": "Hammer of Justice",
  "13": "Cleanse/Purify",
  "14": "Hand of Sacrifice",
  "15": "Avenger's Shield",
  "16": "Lay on Hands",
  "17": "Blessing of Wisdom",
  "18": "Concentration Aura",
  "19": "Seal of Light/Wisdom proc",
  "20": "Judgement of Light/Wisdom",
  "21": "Judgement of Justice",
  "22": "Holy Shock",
  "23": "Divine Protection/Shield",
  "24": "All Judgements",
  "25": "Blessing of Kings",
  "26": "Seal of Command",
  "27": "Crusader+Resistance Auras",
  "28": "Seal of Justice+Righteousness",
  "29": "Blessing of Sanctuary",
  "30": "Righteous Vengeance",
  "31": "Flash of Light",
  "32": "Holy Light",
  "33": "Judgement of Light",
  "34": "Exorcism",
  "35": "Righteous Defense",
  "36": "Damaging Judgements",
  "37": "",
  "38": "",
  "39": "Holy Shield",
  "40": "Hammer of Wrath",
  "41": "Divine Favor",
  "42": "Judgement of Command",
  "43": "",
  "44": "Seal of Corruption/Vengeance",
  "45": "Spiritual Attunement",
  "46": "Avenging Wrath",
  "47": "",
  "48": "Crusader Strike",
  "49": "Holy Shock",
  "50": "Divine Storm",
  "51": "Hammer of the Righteous",
  "52": "Sacred Shield",
  "53": "Shield of Righteousness",
  "54": "Holy Wrath",
  "55": "Judgement of Corruption/Vengeance",
  "56": "Turn Evil",
  "57": "Beacon of Light",
  "58": "Seal of Light",
  "59": "Seal of Wisdom",
  "60": "Sense Undead",
  "61": "Charger/Warhorse (Mount)",
  "62": "Seal of Righteousness",
  "63": "Hand of Reckoning",
  "64": "Dispelable Buffs",
  "65": "Divine Plea",
  "66": "The Art of War",
  "67": "Divine Sacrifice",
  "68": "Judgement of Justice",
  "69": "Judgement of Blood/Martyr",
  "70": "All Auras",
  "71": "Judgements of the Just",
  "72": "Forbearance",
  "73": "Divine Protection",
  "74": "",
  "75": "",
  "76": "",
  "77": "",
  "78": "",
  "79": "",
  "80": "",
  "81": "",
  "82": "",
  "83": "",
  "84": "",
  "85": "",
  "86": "",
  "87": "",
  "88": "",
  "89": "",
  "90": "",
  "91": "",
  "92": "",
  "93": "",
  "94": "",
  "95": "",
  "96": "Gift of the Naaru"
}
